openapi_specgen/__init__.py
openapi_specgen/marshmallow_schema.py
openapi_specgen/openapi.py
openapi_specgen/param.py
openapi_specgen/path.py
openapi_specgen/response.py
openapi_specgen/schema.py
openapi_specgen/security.py
openapi_specgen-1.0.0.dist-info/LICENSE
openapi_specgen-1.0.0.dist-info/METADATA
openapi_specgen-1.0.0.dist-info/WHEEL
openapi_specgen-1.0.0.dist-info/top_level.txt
openapi_specgen-1.0.0.dist-info/RECORD
