Metadata-Version: 2.1
Name: openapi-specgen
Version: 1.0.0
Summary: Generate OpenApi json specification
Home-page: https://github.com/GabrielCappelli/openapi-specgen
Author: Gabriel Cappelli
Author-email: 6148081+GabrielCappelli@users.noreply.github.com
License: MIT
Classifier: License :: OSI Approved :: MIT License
Classifier: Programming Language :: Python :: 3
Classifier: Programming Language :: Python :: 3.8
Classifier: Programming Language :: Python :: 3.9
Classifier: Programming Language :: Python :: 3.10
Classifier: Programming Language :: Python :: 3.11
License-File: LICENSE
Provides-Extra: marshmallow
Requires-Dist: marshmallow (>=3.0.0) ; extra == 'marshmallow'
